acceptance.py
acceptance-0.0.1.dist-info/DESCRIPTION.rst
acceptance-0.0.1.dist-info/METADATA
acceptance-0.0.1.dist-info/RECORD
acceptance-0.0.1.dist-info/WHEEL
acceptance-0.0.1.dist-info/metadata.json
acceptance-0.0.1.dist-info/top_level.txt
