Metadata-Version: 2.0
Name: acceptance
Version: 0.0.1
Summary: Accept Header parsing library
Home-page: https://github.com/blackelk/acceptance
Author: Constantine Parkhimovich
Author-email: cparkhimovich@gmail.com
License: MIT
Keywords: http headers rest
Platform: UNKNOWN
Classifier: Development Status :: 1 - Planning
Classifier: Intended Audience :: Developers
Classifier: Natural Language :: English
Classifier: License :: OSI Approved :: MIT License
Classifier: Operating System :: OS Independent
Classifier: Programming Language :: Python
Classifier: Programming Language :: Python :: 3
Classifier: Programming Language :: Python :: 3.3
Classifier: Programming Language :: Python :: 3.4
Classifier: Programming Language :: Python :: 3.5
Classifier: Topic :: Software Development :: Libraries :: Python Modules
